{
    "forecast": {
        "forecastday": [
            {
                "astro": {
                    "moon_illumination": 35,
                    "moon_phase": "Waxing Crescent",
                    "moonrise": "11:07 AM",
                    "moonset": "10:47 PM",
                    "sunrise": "05:43 AM",
                    "sunset": "05:57 PM"
                },
                "date": "2024-09-10",
                "date_epoch": 1725926400,
                "day": {
                    "avghumidity": 79,
                    "avgtemp_c": 28.1,
                    "avgtemp_f": 82.6,
                    "avgvis_km": 9.8,
                    "avgvis_miles": 6.0,
                    "condition": {
                        "code": 1063,
                        "icon": "//cdn.weatherapi.com/weather/64x64/day/176.png",
                        "text": "Patchy rain possible"
                    },
                    "daily_chance_of_rain": 100,
                    "daily_chance_of_snow": 0,
                    "daily_will_it_rain": 1,
                    "daily_will_it_snow": 0,
                    "maxtemp_c": 32.4,
                    "maxtemp_f": 90.3,
                    "maxwind_kph": 13.3,
                    "maxwind_mph": 8.3,
                    "mintemp_c": 25.2,
                    "mintemp_f": 77.3,
                    "totalprecip_in": 0.07,
                    "totalprecip_mm": 1.87,
                    "totalsnow_cm": 0.0,
                    "uv": 7.0
                },
                "hour": [
                    {
                        "chance_of_rain": 100,
                        "chance_of_snow": 0,
                        "cloud": 73,
                        "condition": {
                            "code": 1150,
                            "icon": "//cdn.weatherapi.com/weather/64x64/night/263.png",
                            "text": "Patchy light drizzle"
                        },
                        "dewpoint_c": 24.1,
                        "dewpoint_f": 75.4,
                        "feelslike_c": 29.6,
                        "feelslike_f": 85.4,
                        "gust_kph": 19.0,
                        "gust_mph": 11.8,
                        "heatindex_c": 29.6,
                        "heatindex_f": 85.4,
                        "humidity": 89,
                        "is_day": 0,
                        "precip_in": 0.02,
                        "precip_mm": 0.41,
                        "pressure_in": 29.75,
                        "pressure_mb": 1007.0,
                        "snow_cm": 0.0,
                        "temp_c": 26.1,
                        "temp_f": 79.0,
                        "time": "2024-09-10 00:00",
                        "time_epoch": 1725901200,
                        "uv": 0.0,
                        "vis_km": 5.0,
                        "vis_miles": 3.0,
                        "will_it_rain": 1,
                        "will_it_snow": 0,
                        "wind_degree": 235,
                        "wind_dir": "SW",
                        "wind_kph": 11.5,
                        "wind_mph": 7.2,
                        "windchill_c": 26.1,
                        "windchill_f": 79.0
                    },
                    {
                        "chance_of_rain": 100,
                        "chance_of_snow": 0,
                        "cloud": 78,
                        "condition": {
                            "code": 1063,
                            "icon": "//cdn.weatherapi.com/weather/64x64/night/176.png",
                            "text": "Patchy rain possible"
                        },
                        "dewpoint_c": 23.9,
                        "dewpoint_f": 75.0,
                        "feelslike_c": 28.6,
                        "feelslike_f": 83.5,
                        "gust_kph": 14.7,
                        "gust_mph": 9.1,
                        "heatindex_c": 28.6,
                        "heatindex_f": 83.5,
                        "humidity": 91,
                        "is_day": 0,
                        "precip_in": 0.04,
                        "precip_mm": 0.91,
                        "pressure_in": 29.73,
                        "pressure_mb": 1007.0,
                        "snow_cm": 0.0,
                        "temp_c": 25.5,
                        "temp_f": 77.8,
                        "time": "2024-09-10 01:00",
                        "time_epoch": 1725904800,
                        "uv": 0.0,
                        "vis_km": 9.0,
                        "vis_miles": 5.0,
                        "will_it_rain": 1,
                        "will_it_snow": 0,
                        "wind_degree": 235,
                        "wind_dir": "SW",
                        "wind_kph": 8.6,
                        "wind_mph": 5.4,
                        "windchill_c": 25.5,
                        "windchill_f": 77.8
                    },
                    {
                        "chance_of_rain": 0,
                        "chance_of_snow": 0,
                        "cloud": 29,
                        "condition": {
                            "code": 1003,
                            "icon": "//cdn.weatherapi.com/weather/64x64/night/116.png",
                            "text": "Partly cloudy"
                        },
                        "dewpoint_c": 23.9,
                        "dewpoint_f": 75.0,
                        "feelslike_c": 28.5,
                        "feelslike_f": 83.3,
                        "gust_kph": 13.2,
                        "gust_mph": 8.2,
                        "heatindex_c": 28.5,
                        "heatindex_f": 83.3,
                        "humidity": 92,
                        "is_day": 0,
                        "precip_in": 0.0,
                        "precip_mm": 0.0,
                        "pressure_in": 29.72,
                        "pressure_mb": 1006.0,
                        "snow_cm": 0.0,
                        "temp_c": 25.4,
                        "temp_f": 77.6,
                        "time": "2024-09-10 02:00",
                        "time_epoch": 1725908400,
                        "uv": 0.0,
                        "vis_km": 10.0,
                        "vis_miles": 6.0,
                        "will_it_rain": 0,
                        "will_it_snow": 0,
                        "wind_degree": 249,
                        "wind_dir": "WSW",
                        "wind_kph": 7.9,
                        "wind_mph": 4.9,
                        "windchill_c": 25.4,
                        "windchill_f": 77.6
                    },
                    {
                        "chance_of_rain": 45,
                        "chance_of_snow": 0,
                        "cloud": 70,
                        "condition": {
                            "code": 1063,
                            "icon": "//cdn.weatherapi.com/weather/64x64/night/176.png",
                            "text": "Patchy rain possible"
                        },
                        "dewpoint_c": 23.9,
                        "dewpoint_f": 75.1,
                        "feelslike_c": 28.4,
                        "feelslike_f": 83.2,
                        "gust_kph": 13.0,
                        "gust_mph": 8.1,
                        "heatindex_c": 28.4,
                        "heatindex_f": 83.2,
                        "humidity": 92,
                        "is_day": 0,
                        "precip_in": 0.0,
                        "precip_mm": 0.08,
                        "pressure_in": 29.7,
                        "pressure_mb": 1006.0,
                        "snow_cm": 0.0,
                        "temp_c": 25.3,
                        "temp_f": 77.5,
                        "time": "2024-09-10 03:00",
                        "time_epoch": 1725912000,
                        "uv": 0.0,
                        "vis_km": 10.0,
                        "vis_miles": 6.0,
                        "will_it_rain": 0,
                        "will_it_snow": 0,
                        "wind_degree": 250,
                        "wind_dir": "WSW",
                        "wind_kph": 7.9,
                        "wind_mph": 4.9,
                        "windchill_c": 25.3,
                        "windchill_f": 77.5
                    },
                    {
                        "chance_of_rain": 0,
                        "chance_of_snow": 0,
                        "cloud": 39,
                        "condition": {
                            "code": 1003,
                            "icon": "//cdn.weatherapi.com/weather/64x64/night/116.png",
                            "text": "Partly cloudy"
                        },
                        "dewpoint_c": 23.9,
                        "dewpoint_f": 75.0,
                        "feelslike_c": 28.3,
                        "feelslike_f": 83.0,
                        "gust_kph": 11.2,
                        "gust_mph": 7.0,
                        "heatindex_c": 28.3,
                        "heatindex_f": 83.0,
                        "humidity": 93,
                        "is_day": 0,
                        "precip_in": 0.0,
                        "precip_mm": 0.0,
                        "pressure_in": 29.71,
                        "pressure_mb": 1006.0,
                        "snow_cm": 0.0,
                        "temp_c": 25.2,
                        "temp_f": 77.4,
                        "time": "2024-09-10 04:00",
                        "time_epoch": 1725915600,
                        "uv": 0.0,
                        "vis_km": 10.0,
                        "vis_miles": 6.0,
                        "will_it_rain": 0,
                        "will_it_snow": 0,
                        "wind_degree": 263,
                        "wind_dir": "W",
                        "wind_kph": 6.8,
                        "wind_mph": 4.3,
                        "windchill_c": 25.2,
                        "windchill_f": 77.4
                    },
                    {
                        "chance_of_rain": 0,
                        "chance_of_snow": 0,
                        "cloud": 40,
                        "condition": {
                            "code": 1003,
                            "icon": "//cdn.weatherapi.com/weather/64x64/night/116.png",
                            "text": "Partly cloudy"
                        },
                        "dewpoint_c": 23.9,
                        "dewpoint_f": 74.9,
                        "feelslike_c": 28.3,
                        "feelslike_f": 82.9,
                        "gust_kph": 10.7,
                        "gust_mph": 6.6,
                        "heatindex_c": 28.3,
                        "heatindex_f": 82.9,
                        "humidity": 92,
                        "is_day": 0,
                        "precip_in": 0.0,
                        "precip_mm": 0.0,
                        "pressure_in": 29.72,
                        "pressure_mb": 1007.0,
                        "snow_cm": 0.0,
                        "temp_c": 25.2,
                        "temp_f": 77.3,
                        "time": "2024-09-10 05:00",
                        "time_epoch": 1725919200,
                        "uv": 0.0,
                        "vis_km": 10.0,
                        "vis_miles": 6.0,
                        "will_it_rain": 0,
                        "will_it_snow": 0,
                        "wind_degree": 260,
                        "wind_dir": "W",
                        "wind_kph": 6.5,
                        "wind_mph": 4.0,
                        "windchill_c": 25.2,
                        "windchill_f": 77.3
                    },
                    {
                        "chance_of_rain": 0,
                        "chance_of_snow": 0,
                        "cloud": 40,
                        "condition": {
                            "code": 1003,
                            "icon": "//cdn.weatherapi.com/weather/64x64/day/116.png",
                            "text": "Partly cloudy"
                        },
                        "dewpoint_c": 23.9,
                        "dewpoint_f": 75.0,
                        "feelslike_c": 28.3,
                        "feelslike_f": 83.0,
                        "gust_kph": 12.2,
                        "gust_mph": 7.6,
                        "heatindex_c": 28.3,
                        "heatindex_f": 83.0,
                        "humidity": 92,
                        "is_day": 1,
                        "precip_in": 0.0,
                        "precip_mm": 0.0,
                        "pressure_in": 29.74,
                        "pressure_mb": 1007.0,
                        "snow_cm": 0.0,
                        "temp_c": 25.2,
                        "temp_f": 77.4,
                        "time": "2024-09-10 06:00",
                        "time_epoch": 1725922800,
                        "uv": 7.0,
                        "vis_km": 10.0,
                        "vis_miles": 6.0,
                        "will_it_rain": 0,
                        "will_it_snow": 0,
                        "wind_degree": 267,
                        "wind_dir": "W",
                        "wind_kph": 7.6,
                        "wind_mph": 4.7,
                        "windchill_c": 25.2,
                        "windchill_f": 77.4
                    },
                    {
                        "chance_of_rain": 0,
                        "chance_of_snow": 0,
                        "cloud": 36,
                        "condition": {
                            "code": 1003,
                            "icon": "//cdn.weatherapi.com/weather/64x64/day/116.png",
                            "text": "Partly cloudy"
                        },
                        "dewpoint_c": 24.0,
                        "dewpoint_f": 75.3,
                        "feelslike_c": 29.5,
                        "feelslike_f": 85.1,
                        "gust_kph": 15.3,
                        "gust_mph": 9.5,
                        "heatindex_c": 29.5,
                        "heatindex_f": 85.1,
                        "humidity": 89,
                        "is_day": 1,
                        "precip_in": 0.0,
                        "precip_mm": 0.0,
                        "pressure_in": 29.76,
                        "pressure_mb": 1008.0,
                        "snow_cm": 0.0,
                        "temp_c": 26.1,
                        "temp_f": 78.9,
                        "time": "2024-09-10 07:00",
                        "time_epoch": 1725926400,
                        "uv": 7.0,
                        "vis_km": 10.0,
                        "vis_miles": 6.0,
                        "will_it_rain": 0,
                        "will_it_snow": 0,
                        "wind_degree": 276,
                        "wind_dir": "W",
                        "wind_kph": 10.8,
                        "wind_mph": 6.7,
                        "windchill_c": 26.1,
                        "windchill_f": 78.9
                    },
                    {
                        "chance_of_rain": 0,
                        "chance_of_snow": 0,
                        "cloud": 38,
                        "condition": {
                            "code": 1003,
                            "icon": "//cdn.weatherapi.com/weather/64x64/day/116.png",
                            "text": "Partly cloudy"
                        },
                        "dewpoint_c": 23.9,
                        "dewpoint_f": 75.0,
                        "feelslike_c": 30.8,
                        "feelslike_f": 87.4,
                        "gust_kph": 15.0,
                        "gust_mph": 9.4,
                        "heatindex_c": 30.8,
                        "heatindex_f": 87.4,
                        "humidity": 83,
                        "is_day": 1,
                        "precip_in": 0.0,
                        "precip_mm": 0.0,
                        "pressure_in": 29.78,
                        "pressure_mb": 1009.0,
                        "snow_cm": 0.0,
                        "temp_c": 27.1,
                        "temp_f": 80.8,
                        "time": "2024-09-10 08:00",
                        "time_epoch": 1725930000,
                        "uv": 7.0,
                        "vis_km": 10.0,
                        "vis_miles": 6.0,
                        "will_it_rain": 0,
                        "will_it_snow": 0,
                        "wind_degree": 287,
                        "wind_dir": "WNW",
                        "wind_kph": 11.5,
                        "wind_mph": 7.2,
                        "windchill_c": 27.1,
                        "windchill_f": 80.8
                    },
                    {
                        "chance_of_rain": 0,
                        "chance_of_snow": 0,
                        "cloud": 61,
                        "condition": {
                            "code": 1003,
                            "icon": "//cdn.weatherapi.com/weather/64x64/day/116.png",
                            "text": "Partly cloudy"
                        },
                        "dewpoint_c": 23.6,
                        "dewpoint_f": 74.6,
                        "feelslike_c": 31.9,
                        "feelslike_f": 89.4,
                        "gust_kph": 14.4,
                        "gust_mph": 9.0,
                        "heatindex_c": 31.9,
                        "heatindex_f": 89.4,
                        "humidity": 77,
                        "is_day": 1,
                        "precip_in": 0.0,
                        "precip_mm": 0.0,
                        "pressure_in": 29.79,
                        "pressure_mb": 1009.0,
                        "snow_cm": 0.0,
                        "temp_c": 28.0,
                        "temp_f": 82.4,
                        "time": "2024-09-10 09:00",
                        "time_epoch": 1725933600,
                        "uv": 7.0,
                        "vis_km": 10.0,
                        "vis_miles": 6.0,
                        "will_it_rain": 0,
                        "will_it_snow": 0,
                        "wind_degree": 290,
                        "wind_dir": "WNW",
                        "wind_kph": 11.5,
                        "wind_mph": 7.2,
                        "windchill_c": 28.0,
                        "windchill_f": 82.4
                    },
                    {
                        "chance_of_rain": 45,
                        "chance_of_snow": 0,
                        "cloud": 90,
                        "condition": {
                            "code": 1009,
                            "icon": "//cdn.weatherapi.com/weather/64x64/day/122.png",
                            "text": "Overcast"
                        },
                        "dewpoint_c": 23.7,
                        "dewpoint_f": 74.6,
                        "feelslike_c": 33.8,
                        "feelslike_f": 92.8,
                        "gust_kph": 13.7,
                        "gust_mph": 8.5,
                        "heatindex_c": 33.8,
                        "heatindex_f": 92.8,
                        "humidity": 72,
                        "is_day": 1,
                        "precip_in": 0.0,
                        "precip_mm": 0.0,
                        "pressure_in": 29.78,
                        "pressure_mb": 1009.0,
                        "snow_cm": 0.0,
                        "temp_c": 29.3,
                        "temp_f": 84.8,
                        "time": "2024-09-10 10:00",
                        "time_epoch": 1725937200,
                        "uv": 6.0,
                        "vis_km": 10.0,
                        "vis_miles": 6.0,
                        "will_it_rain": 0,
                        "will_it_snow": 0,
                        "wind_degree": 288,
                        "wind_dir": "WNW",
                        "wind_kph": 11.9,
                        "wind_mph": 7.4,
                        "windchill_c": 29.3,
                        "windchill_f": 84.8
                    },
                    {
                        "chance_of_rain": 45,
                        "chance_of_snow": 0,
                        "cloud": 98,
                        "condition": {
                            "code": 1063,
                            "icon": "//cdn.weatherapi.com/weather/64x64/day/176.png",
                            "text": "Patchy rain possible"
                        },
                        "dewpoint_c": 23.7,
                        "dewpoint_f": 74.7,
                        "feelslike_c": 35.8,
                        "feelslike_f": 96.4,
                        "gust_kph": 14.5,
                        "gust_mph": 9.0,
                        "heatindex_c": 35.8,
                        "heatindex_f": 96.4,
                        "humidity": 67,
                        "is_day": 1,
                        "precip_in": 0.0,
                        "precip_mm": 0.01,
                        "pressure_in": 29.77,
                        "pressure_mb": 1008.0,
                        "snow_cm": 0.0,
                        "temp_c": 30.7,
                        "temp_f": 87.2,
                        "time": "2024-09-10 11:00",
                        "time_epoch": 1725940800,
                        "uv": 7.0,
                        "vis_km": 10.0,
                        "vis_miles": 6.0,
                        "will_it_rain": 0,
                        "will_it_snow": 0,
                        "wind_degree": 283,
                        "wind_dir": "WNW",
                        "wind_kph": 12.6,
                        "wind_mph": 7.8,
                        "windchill_c": 30.7,
                        "windchill_f": 87.2
                    },
                    {
                        "chance_of_rain": 45,
                        "chance_of_snow": 0,
                        "cloud": 84,
                        "condition": {
                            "code": 1063,
                            "icon": "//cdn.weatherapi.com/weather/64x64/day/176.png",
                            "text": "Patchy rain possible"
                        },
                        "dewpoint_c": 23.6,
                        "dewpoint_f": 74.4,
                        "feelslike_c": 36.8,
                        "feelslike_f": 98.3,
                        "gust_kph": 14.5,
                        "gust_mph": 9.0,
                        "heatindex_c": 36.8,
                        "heatindex_f": 98.3,
                        "humidity": 63,
                        "is_day": 1,
                        "precip_in": 0.0,
                        "precip_mm": 0.02,
                        "pressure_in": 29.73,
                        "pressure_mb": 1007.0,
                        "snow_cm": 0.0,
                        "temp_c": 31.5,
                        "temp_f": 88.7,
                        "time": "2024-09-10 12:00",
                        "time_epoch": 1725944400,
                        "uv": 7.0,
                        "vis_km": 10.0,
                        "vis_miles": 6.0,
                        "will_it_rain": 0,
                        "will_it_snow": 0,
                        "wind_degree": 281,
                        "wind_dir": "WNW",
                        "wind_kph": 12.6,
                        "wind_mph": 7.8,
                        "windchill_c": 31.5,
                        "windchill_f": 88.7
                    },
                    {
                        "chance_of_rain": 45,
                        "chance_of_snow": 0,
                        "cloud": 51,
                        "condition": {
                            "code": 1063,
                            "icon": "//cdn.weatherapi.com/weather/64x64/day/176.png",
                            "text": "Patchy rain possible"
                        },
                        "dewpoint_c": 23.4,
                        "dewpoint_f": 74.1,
                        "feelslike_c": 37.2,
                        "feelslike_f": 99.0,
                        "gust_kph": 15.3,
                        "gust_mph": 9.5,
                        "heatindex_c": 37.2,
                        "heatindex_f": 99.0,
                        "humidity": 61,
                        "is_day": 1,
                        "precip_in": 0.0,
                        "precip_mm": 0.02,
                        "pressure_in": 29.69,
                        "pressure_mb": 1005.0,
                        "snow_cm": 0.0,
                        "temp_c": 31.9,
                        "temp_f": 89.4,
                        "time": "2024-09-10 13:00",
                        "time_epoch": 1725948000,
                        "uv": 7.0,
                        "vis_km": 10.0,
                        "vis_miles": 6.0,
                        "will_it_rain": 0,
                        "will_it_snow": 0,
                        "wind_degree": 279,
                        "wind_dir": "W",
                        "wind_kph": 13.3,
                        "wind_mph": 8.3,
                        "windchill_c": 31.9,
                        "windchill_f": 89.4
                    },
                    {
                        "chance_of_rain": 45,
                        "chance_of_snow": 0,
                        "cloud": 92,
                        "condition": {
                            "code": 1063,
                            "icon": "//cdn.weatherapi.com/weather/64x64/day/176.png",
                            "text": "Patchy rain possible"
                        },
                        "dewpoint_c": 23.1,
                        "dewpoint_f": 73.6,
                        "feelslike_c": 37.7,
                        "feelslike_f": 99.8,
                        "gust_kph": 15.0,
                        "gust_mph": 9.3,
                        "heatindex_c": 37.7,
                        "heatindex_f": 99.8,
                        "humidity": 58,
                        "is_day": 1,
                        "precip_in": 0.0,
                        "precip_mm": 0.09,
                        "pressure_in": 29.66,
                        "pressure_mb": 1005.0,
                        "snow_cm": 0.0,
                        "temp_c": 32.4,
                        "temp_f": 90.3,
                        "time": "2024-09-10 14:00",
                        "time_epoch": 1725951600,
                        "uv": 7.0,
                        "vis_km": 10.0,
                        "vis_miles": 6.0,
                        "will_it_rain": 0,
                        "will_it_snow": 0,
                        "wind_degree": 279,
                        "wind_dir": "W",
                        "wind_kph": 12.6,
                        "wind_mph": 7.8,
                        "windchill_c": 32.4,
                        "windchill_f": 90.3
                    },
                    {
                        "chance_of_rain": 100,
                        "chance_of_snow": 0,
                        "cloud": 91,
                        "condition": {
                            "code": 1063,
                            "icon": "//cdn.weatherapi.com/weather/64x64/day/176.png",
                            "text": "Patchy rain possible"
                        },
                        "dewpoint_c": 23.5,
                        "dewpoint_f": 74.2,
                        "feelslike_c": 37.4,
                        "feelslike_f": 99.4,
                        "gust_kph": 15.0,
                        "gust_mph": 9.3,
                        "heatindex_c": 37.4,
                        "heatindex_f": 99.4,
                        "humidity": 61,
                        "is_day": 1,
                        "precip_in": 0.0,
                        "precip_mm": 0.1,
                        "pressure_in": 29.66,
                        "pressure_mb": 1004.0,
                        "snow_cm": 0.0,
                        "temp_c": 32.0,
                        "temp_f": 89.6,
                        "time": "2024-09-10 15:00",
                        "time_epoch": 1725955200,
                        "uv": 7.0,
                        "vis_km": 10.0,
                        "vis_miles": 6.0,
                        "will_it_rain": 1,
                        "will_it_snow": 0,
                        "wind_degree": 274,
                        "wind_dir": "W",
                        "wind_kph": 11.5,
                        "wind_mph": 7.2,
                        "windchill_c": 32.0,
                        "windchill_f": 89.6
                    },
                    {
                        "chance_of_rain": 100,
                        "chance_of_snow": 0,
                        "cloud": 79,
                        "condition": {
                            "code": 1063,
                            "icon": "//cdn.weatherapi.com/weather/64x64/day/176.png",
                            "text": "Patchy rain possible"
                        },
                        "dewpoint_c": 23.8,
                        "dewpoint_f": 74.9,
                        "feelslike_c": 36.6,
                        "feelslike_f": 97.9,
                        "gust_kph": 15.2,
                        "gust_mph": 9.4,
                        "heatindex_c": 36.6,
                        "heatindex_f": 97.9,
                        "humidity": 65,
                        "is_day": 1,
                        "precip_in": 0.0,
                        "precip_mm": 0.1,
                        "pressure_in": 29.66,
                        "pressure_mb": 1004.0,
                        "snow_cm": 0.0,
                        "temp_c": 31.2,
                        "temp_f": 88.1,
                        "time": "2024-09-10 16:00",
                        "time_epoch": 1725958800,
                        "uv": 7.0,
                        "vis_km": 10.0,
                        "vis_miles": 6.0,
                        "will_it_rain": 1,
                        "will_it_snow": 0,
                        "wind_degree": 266,
                        "wind_dir": "W",
                        "wind_kph": 10.4,
                        "wind_mph": 6.5,
                        "windchill_c": 31.2,
                        "windchill_f": 88.1
                    },
                    {
                        "chance_of_rain": 100,
                        "chance_of_snow": 0,
                        "cloud": 59,
                        "condition": {
                            "code": 1063,
                            "icon": "//cdn.weatherapi.com/weather/64x64/day/176.png",
                            "text": "Patchy rain possible"
                        },
                        "dewpoint_c": 24.0,
                        "dewpoint_f": 75.2,
                        "feelslike_c": 35.3,
                        "feelslike_f": 95.5,
                        "gust_kph": 15.2,
                        "gust_mph": 9.4,
                        "heatindex_c": 35.3,
                        "heatindex_f": 95.5,
                        "humidity": 70,
                        "is_day": 1,
                        "precip_in": 0.0,
                        "precip_mm": 0.11,
                        "pressure_in": 29.67,
                        "pressure_mb": 1005.0,
                        "snow_cm": 0.0,
                        "temp_c": 30.2,
                        "temp_f": 86.3,
                        "time": "2024-09-10 17:00",
                        "time_epoch": 1725962400,
                        "uv": 7.0,
                        "vis_km": 10.0,
                        "vis_miles": 6.0,
                        "will_it_rain": 1,
                        "will_it_snow": 0,
                        "wind_degree": 255,
                        "wind_dir": "WSW",
                        "wind_kph": 9.4,
                        "wind_mph": 5.8,
                        "windchill_c": 30.2,
                        "windchill_f": 86.3
                    },
                    {
                        "chance_of_rain": 45,
                        "chance_of_snow": 0,
                        "cloud": 53,
                        "condition": {
                            "code": 1063,
                            "icon": "//cdn.weatherapi.com/weather/64x64/night/176.png",
                            "text": "Patchy rain possible"
                        },
                        "dewpoint_c": 23.8,
                        "dewpoint_f": 74.8,
                        "feelslike_c": 33.6,
                        "feelslike_f": 92.5,
                        "gust_kph": 17.6,
                        "gust_mph": 11.0,
                        "heatindex_c": 33.6,
                        "heatindex_f": 92.5,
                        "humidity": 73,
                        "is_day": 0,
                        "precip_in": 0.0,
                        "precip_mm": 0.03,
                        "pressure_in": 29.69,
                        "pressure_mb": 1006.0,
                        "snow_cm": 0.0,
                        "temp_c": 29.1,
                        "temp_f": 84.4,
                        "time": "2024-09-10 18:00",
                        "time_epoch": 1725966000,
                        "uv": 0.0,
                        "vis_km": 10.0,
                        "vis_miles": 6.0,
                        "will_it_rain": 0,
                        "will_it_snow": 0,
                        "wind_degree": 247,
                        "wind_dir": "WSW",
                        "wind_kph": 10.1,
                        "wind_mph": 6.3,
                        "windchill_c": 29.1,
                        "windchill_f": 84.4
                    },
                    {
                        "chance_of_rain": 45,
                        "chance_of_snow": 0,
                        "cloud": 41,
                        "condition": {
                            "code": 1003,
                            "icon": "//cdn.weatherapi.com/weather/64x64/night/116.png",
                            "text": "Partly cloudy"
                        },
                        "dewpoint_c": 23.9,
                        "dewpoint_f": 75.0,
                        "feelslike_c": 32.7,
                        "feelslike_f": 90.9,
                        "gust_kph": 19.2,
                        "gust_mph": 11.9,
                        "heatindex_c": 32.7,
                        "heatindex_f": 90.9,
                        "humidity": 76,
                        "is_day": 0,
                        "precip_in": 0.0,
                        "precip_mm": 0.0,
                        "pressure_in": 29.72,
                        "pressure_mb": 1006.0,
                        "snow_cm": 0.0,
                        "temp_c": 28.5,
                        "temp_f": 83.2,
                        "time": "2024-09-10 19:00",
                        "time_epoch": 1725969600,
                        "uv": 0.0,
                        "vis_km": 10.0,
                        "vis_miles": 6.0,
                        "will_it_rain": 0,
                        "will_it_snow": 0,
                        "wind_degree": 241,
                        "wind_dir": "WSW",
                        "wind_kph": 11.2,
                        "wind_mph": 6.9,
                        "windchill_c": 28.5,
                        "windchill_f": 83.2
                    },
                    {
                        "chance_of_rain": 45,
                        "chance_of_snow": 0,
                        "cloud": 71,
                        "condition": {
                            "code": 1063,
                            "icon": "//cdn.weatherapi.com/weather/64x64/night/176.png",
                            "text": "Patchy rain possible"
                        },
                        "dewpoint_c": 24.0,
                        "dewpoint_f": 75.2,
                        "feelslike_c": 32.3,
                        "feelslike_f": 90.1,
                        "gust_kph": 20.1,
                        "gust_mph": 12.5,
                        "heatindex_c": 32.3,
                        "heatindex_f": 90.1,
                        "humidity": 78,
                        "is_day": 0,
                        "precip_in": 0.0,
                        "precip_mm": 0.01,
                        "pressure_in": 29.74,
                        "pressure_mb": 1007.0,
                        "snow_cm": 0.0,
                        "temp_c": 28.1,
                        "temp_f": 82.6,
                        "time": "2024-09-10 20:00",
                        "time_epoch": 1725973200,
                        "uv": 0.0,
                        "vis_km": 10.0,
                        "vis_miles": 6.0,
                        "will_it_rain": 0,
                        "will_it_snow": 0,
                        "wind_degree": 242,
                        "wind_dir": "WSW",
                        "wind_kph": 12.2,
                        "wind_mph": 7.6,
                        "windchill_c": 28.1,
                        "windchill_f": 82.6
                    },
                    {
                        "chance_of_rain": 45,
                        "chance_of_snow": 0,
                        "cloud": 44,
                        "condition": {
                            "code": 1003,
                            "icon": "//cdn.weatherapi.com/weather/64x64/night/116.png",
                            "text": "Partly cloudy"
                        },
                        "dewpoint_c": 24.1,
                        "dewpoint_f": 75.3,
                        "feelslike_c": 31.3,
                        "feelslike_f": 88.3,
                        "gust_kph": 20.8,
                        "gust_mph": 12.9,
                        "heatindex_c": 31.3,
                        "heatindex_f": 88.3,
                        "humidity": 82,
                        "is_day": 0,
                        "precip_in": 0.0,
                        "precip_mm": 0.0,
                        "pressure_in": 29.77,
                        "pressure_mb": 1008.0,
                        "snow_cm": 0.0,
                        "temp_c": 27.4,
                        "temp_f": 81.3,
                        "time": "2024-09-10 21:00",
                        "time_epoch": 1725976800,
                        "uv": 0.0,
                        "vis_km": 10.0,
                        "vis_miles": 6.0,
                        "will_it_rain": 0,
                        "will_it_snow": 0,
                        "wind_degree": 238,
                        "wind_dir": "WSW",
                        "wind_kph": 13.0,
                        "wind_mph": 8.1,
                        "windchill_c": 27.4,
                        "windchill_f": 81.3
                    },
                    {
                        "chance_of_rain": 0,
                        "chance_of_snow": 0,
                        "cloud": 40,
                        "condition": {
                            "code": 1003,
                            "icon": "//cdn.weatherapi.com/weather/64x64/night/116.png",
                            "text": "Partly cloudy"
                        },
                        "dewpoint_c": 24.1,
                        "dewpoint_f": 75.4,
                        "feelslike_c": 30.7,
                        "feelslike_f": 87.2,
                        "gust_kph": 19.8,
                        "gust_mph": 12.3,
                        "heatindex_c": 30.7,
                        "heatindex_f": 87.2,
                        "humidity": 85,
                        "is_day": 0,
                        "precip_in": 0.0,
                        "precip_mm": 0.0,
                        "pressure_in": 29.78,
                        "pressure_mb": 1009.0,
                        "snow_cm": 0.0,
                        "temp_c": 26.9,
                        "temp_f": 80.4,
                        "time": "2024-09-10 22:00",
                        "time_epoch": 1725980400,
                        "uv": 0.0,
                        "vis_km": 10.0,
                        "vis_miles": 6.0,
                        "will_it_rain": 0,
                        "will_it_snow": 0,
                        "wind_degree": 236,
                        "wind_dir": "WSW",
                        "wind_kph": 12.6,
                        "wind_mph": 7.8,
                        "windchill_c": 26.9,
                        "windchill_f": 80.4
                    },
                    {
                        "chance_of_rain": 0,
                        "chance_of_snow": 0,
                        "cloud": 40,
                        "condition": {
                            "code": 1003,
                            "icon": "//cdn.weatherapi.com/weather/64x64/night/116.png",
                            "text": "Partly cloudy"
                        },
                        "dewpoint_c": 24.1,
                        "dewpoint_f": 75.5,
                        "feelslike_c": 30.2,
                        "feelslike_f": 86.3,
                        "gust_kph": 19.3,
                        "gust_mph": 12.0,
                        "heatindex_c": 30.2,
                        "heatindex_f": 86.3,
                        "humidity": 87,
                        "is_day": 0,
                        "precip_in": 0.0,
                        "precip_mm": 0.0,
                        "pressure_in": 29.77,
                        "pressure_mb": 1008.0,
                        "snow_cm": 0.0,
                        "temp_c": 26.5,
                        "temp_f": 79.7,
                        "time": "2024-09-10 23:00",
                        "time_epoch": 1725984000,
                        "uv": 0.0,
                        "vis_km": 10.0,
                        "vis_miles": 6.0,
                        "will_it_rain": 0,
                        "will_it_snow": 0,
                        "wind_degree": 236,
                        "wind_dir": "WSW",
                        "wind_kph": 12.2,
                        "wind_mph": 7.6,
                        "windchill_c": 26.5,
                        "windchill_f": 79.7
                    }
                ]
            }
        ]
    },
    "location": {
        "country": "Vietnam",
        "lat": 10.75,
        "localtime": "2024-12-13 00:52",
        "localtime_epoch": 1734025973,
        "lon": 106.6667,
        "name": "Saigon",
        "region": "",
        "tz_id": "Asia/Ho_Chi_Minh"
    }
}